{
  "networks": {
    "Arbitrum": {
      "lastIndexedBlock": 191106592,
      "lastUpdated": "2025-09-05T05:33:20-04:00"
    },
    "Base": {
      "lastIndexedBlock": 30648187,
      "lastUpdated": "2025-09-05T05:34:16-04:00"
    },
    "Ethereum": {
      "lastIndexedBlock": 9137953,
      "lastUpdated": "2025-09-05T05:32:08-04:00"
    },
    "Optimism": {
      "lastIndexedBlock": 32631060,
      "lastUpdated": "2025-09-05T05:32:19-04:00"
    },
    "Starknet": {
      "lastIndexedBlock": 1890451,
      "lastUpdated": "2025-09-05T05:34:15-04:00"
    }
  }
}